auto_auth/__init__.py
auto_auth/auto_auth.py
auto_auth-1.0.9.dist-info/LICENSE
auto_auth-1.0.9.dist-info/METADATA
auto_auth-1.0.9.dist-info/WHEEL
auto_auth-1.0.9.dist-info/top_level.txt
auto_auth-1.0.9.dist-info/RECORD
